{
  "sendgrid_verification": false,
  "sendgrid_options": {
    "api_key": "YOUR_SENDGRID_API_KEY",
    "sendFromEmail": "THE EMAIL THE CODES WILL BE SENT FROM (MUST BE VERIFIED IN SENDGRID)",
    "to_email": "THE EMAIL YOU WANT THE CODES SENT TO"
  },

  "discord_verification": false,
  "webhook_url": "YOUR DISCORD WEBHOOK URL",

  "smtp_verification": false,
  "smtp_options": {
    "to_email": "THE EMAIL YOU WANT THE CODES SENT TO",
    "sendFromEmail": "THE EMAIL THE CODES ARE SENT FROM",
    "host": "YOUR SMTP HOST",
    "port": 465,
    "auth": {
      "user": "SMTP USER",
      "pass": "YOUR PASSWORD"
    }
  }
}
